torch_cgd/__init__.py
torch_cgd/acgd.py
torch_cgd/cgd.py
torch_cgd/cgd_cg.py
torch_cgd/utils.py
torch_cgd/solvers/__init__.py
torch_cgd/solvers/cg.py
torch_cgd/solvers/gmres.py
torch_cgd-0.0.2.dist-info/LICENSE
torch_cgd-0.0.2.dist-info/METADATA
torch_cgd-0.0.2.dist-info/WHEEL
torch_cgd-0.0.2.dist-info/top_level.txt
torch_cgd-0.0.2.dist-info/RECORD
