Metadata-Version: 2.1
Name: torch-cgd
Version: 0.0.2
Summary: A fast and memory-saving implementation of competitive gradient descent in PyTorch
Author-email: Thomas Wagenaar <wagenaartje@protonmail.com>
License: MIT License
Project-URL: repository, https://github.com/wagenaartje/torch-cgd
Requires-Python: >=3.9
License-File: LICENSE
Requires-Dist: torch
